zzstocklib_pkg/KZZUtility.py
zzstocklib_pkg/__init__.py
zzstocklib_pkg/dealwith_notification.py
zzstocklib_pkg/genKZZreport.py
zzstocklib_pkg/genStockreport.py
zzstocklib_pkg/propertiesUtility.py
zzstocklib_pkg/sinaFinanceUtility.py
zzstocklib_pkg/wx_notification.py
zzstocklib_pkg/zzlogger.py
zzstocklib_pkg_pubbyzz-0.0.2.dist-info/LICENSE
zzstocklib_pkg_pubbyzz-0.0.2.dist-info/METADATA
zzstocklib_pkg_pubbyzz-0.0.2.dist-info/WHEEL
zzstocklib_pkg_pubbyzz-0.0.2.dist-info/top_level.txt
zzstocklib_pkg_pubbyzz-0.0.2.dist-info/RECORD
