Metadata-Version: 2.1
Name: zzstocklib-pkg-pubbyzz
Version: 0.0.2
Summary: A Stock Analysis Lib
Home-page: https://github.com/pubbyzz/zzstocklib
Author: pubbyzz
Author-email: pubbyzz@hotmail.com
License: UNKNOWN
Platform: UNKNOWN
Classifier: Programming Language :: Python :: 3
Classifier: License :: OSI Approved :: MIT License
Classifier: Operating System :: OS Independent
